hglib/__init__.py
hglib/client.py
hglib/context.py
hglib/error.py
hglib/merge.py
hglib/templates.py
hglib/util.py
hglib-2.6.2.dist-info/LICENSE
hglib-2.6.2.dist-info/METADATA
hglib-2.6.2.dist-info/WHEEL
hglib-2.6.2.dist-info/top_level.txt
hglib-2.6.2.dist-info/RECORD
